bicpl/__init__.py
bicpl/_version.py
bicpl/civet.py
bicpl/math.py
bicpl/obj.py
bicpl/types.py
bicpl/wavefront.py
pybicpl-0.5.1.dist-info/LICENSE
pybicpl-0.5.1.dist-info/METADATA
pybicpl-0.5.1.dist-info/WHEEL
pybicpl-0.5.1.dist-info/entry_points.txt
pybicpl-0.5.1.dist-info/top_level.txt
pybicpl-0.5.1.dist-info/RECORD
